odoo/addons/shopfloor_workstation_label_printer/README.rst
odoo/addons/shopfloor_workstation_label_printer/__init__.py
odoo/addons/shopfloor_workstation_label_printer/__manifest__.py
odoo/addons/shopfloor_workstation_label_printer/i18n/it.po
odoo/addons/shopfloor_workstation_label_printer/i18n/shopfloor_workstation_label_printer.pot
odoo/addons/shopfloor_workstation_label_printer/models/__init__.py
odoo/addons/shopfloor_workstation_label_printer/models/shopfloor_workstation.py
odoo/addons/shopfloor_workstation_label_printer/readme/CONTRIBUTORS.md
odoo/addons/shopfloor_workstation_label_printer/readme/DESCRIPTION.md
odoo/addons/shopfloor_workstation_label_printer/static/description/icon.png
odoo/addons/shopfloor_workstation_label_printer/static/description/index.html
odoo/addons/shopfloor_workstation_label_printer/views/shopfloor_workstation.xml
odoo_addon_shopfloor_workstation_label_printer-18.0.1.0.0.2.dist-info/METADATA
odoo_addon_shopfloor_workstation_label_printer-18.0.1.0.0.2.dist-info/WHEEL
odoo_addon_shopfloor_workstation_label_printer-18.0.1.0.0.2.dist-info/top_level.txt
odoo_addon_shopfloor_workstation_label_printer-18.0.1.0.0.2.dist-info/RECORD
