Metadata-Version: 2.1
Name: odoo-addon-shopfloor_workstation_label_printer
Version: 18.0.1.0.0.2
Requires-Python: >=3.10
Requires-Dist: odoo-addon-base_report_to_label_printer==18.0.*
Requires-Dist: odoo-addon-shopfloor_workstation==18.0.*
Requires-Dist: odoo==18.0.*
Summary: Adds a label printer configuration to shopfloor workstation.
Home-page: https://github.com/OCA/shopfloor-app
License: AGPL-3
Author: Camptocamp, Odoo Community Association (OCA)
Author-email: support@odoo-community.org
Classifier: Programming Language :: Python
Classifier: Framework :: Odoo
Classifier: Framework :: Odoo :: 18.0
Classifier: License :: OSI Approved :: GNU Affero General Public License v3
Classifier: Development Status :: 3 - Alpha
